CONTRIBUTING.rst
LICENCE.rst
MANIFEST.in
README.rst
requirements.txt
setup.cfg
setup.py
.github/workflows/publish.yml
bin/feature_merge
feature_merge/__init__.py
feature_merge/__main__.py
feature_merge/__version.py
feature_merge/merge_criteria.py
feature_merge.egg-info/PKG-INFO
feature_merge.egg-info/SOURCES.txt
feature_merge.egg-info/dependency_links.txt
feature_merge.egg-info/entry_points.txt
feature_merge.egg-info/not-zip-safe
feature_merge.egg-info/pbr.json
feature_merge.egg-info/requires.txt
feature_merge.egg-info/top_level.txt
test-data/1015597_genome.gbk_1.gff3
test-data/1015597_genome.gbk_2.gff3
test-data/615598_genome.gbk_1.gff3
test-data/615598_genome.gbk_2.gff3
test-data/915596_genome.gbk_1.gff3
test-data/915596_genome.gbk_2.gff3
test-data/empty_test.gff
test-data/empty_test_header.gff
test-data/synthetic.gff3
tests/__init__.py
tests/test_load_data.py
tests/test_merge.py
tests/test_merge_all.py