Metadata-Version: 2.1
Name: feature-merge
Version: 1.3.0
Summary: Merge overlapping features of GFF/GTF files.
Home-page: https://github.com/brinkmanlab/feature_merge
Author: Nolan Woods
Author-email: nolan_w@sfu.ca
License: MIT Amended
Keywords: merge,bioinformatics,gff,features,overlap
Platform: UNKNOWN
Classifier: Environment :: Console
Classifier: Intended Audience :: Science/Research
Classifier: License :: OSI Approved :: MIT License
Classifier: Operating System :: POSIX
Classifier: Programming Language :: Python :: 3.7
Classifier: Topic :: Scientific/Engineering :: Bio-Informatics
